checks_dev_cli/__init__.py
checks_dev_cli/check.py
checks_dev_cli/cli.py
checks_dev_cli/conf.py
checks_dev_cli/expect.py
checks_dev_cli/file_utils.py
checks_dev_cli-0.2.0.dist-info/METADATA
checks_dev_cli-0.2.0.dist-info/WHEEL
checks_dev_cli-0.2.0.dist-info/entry_points.txt
checks_dev_cli-0.2.0.dist-info/RECORD
