Metadata-Version: 2.1
Name: checks-dev-cli
Version: 0.2.0
Summary: 
Author: Ideatives Inc
Author-email: info@ideatives.com
Requires-Python: >=3.11,<4.0
Classifier: Programming Language :: Python :: 3
Classifier: Programming Language :: Python :: 3.11
Classifier: Programming Language :: Python :: 3.12
Requires-Dist: croniter (>=2.0.5,<3.0.0)
Requires-Dist: pydantic (>=2.7.3,<3.0.0)
Requires-Dist: pyyaml (>=6.0.1,<7.0.0)
Requires-Dist: synthetic-open-schema-model (==0.1.0)
Requires-Dist: typer (>=0.12.3,<0.13.0)
